qprofiler/__init__.py
qprofiler/metadata/__init__.py
qprofiler/metadata/db.py
qprofiler/metadata/filesystem.py
qprofiler/profiler.py
qprofiler/qcheck.py
qprofiler/scan.py
qprofiler/tests/__init__.py
qprofiler/tests/test_profiler.py
qprofiler/tests/test_qpipeline.py
qprofiler/tests/test_qtest.py
qprofiler/utils/__init__.py
qprofiler/utils/dir_tree.py
qprofiler/utils/message.py
qprofiler-0.3.0.dist-info/LICENSE
qprofiler-0.3.0.dist-info/METADATA
qprofiler-0.3.0.dist-info/WHEEL
qprofiler-0.3.0.dist-info/RECORD
