Metadata-Version: 2.1
Name: qprofiler
Version: 0.3.0
Summary: profile tabular datasets, manage automatic validation for new datasets, automatic handling for quality issues.
Home-page: https://github.com/Ezzaldin97/dprofiler
License: MIT
Author: Ezzaldin97
Author-email: kingtal632@yahoo.com
Requires-Python: >=3.10,<4.0
Classifier: License :: OSI Approved :: MIT License
Classifier: Programming Language :: Python :: 3
Classifier: Programming Language :: Python :: 3.10
Classifier: Programming Language :: Python :: 3.11
Requires-Dist: colorama (>=0.4.4,<0.5.0)
Requires-Dist: pathlib (>=1.0,<2.0)
Requires-Dist: polars[all] (>=0.19.0,<0.20.0)
Requires-Dist: pyyaml (>=6.0.1,<7.0.0)
Requires-Dist: ruamel-yaml (>=0.17.32,<0.18.0)
Requires-Dist: typing-extensions (>=4.7.0,<5.0.0)
Project-URL: Repository, https://github.com/Ezzaldin97/dprofiler
